[{"players":[{"race":"zerg","name":"PREDATOR","region":"EU","url":"http:\/\/www.sc2ranks.com\/eu\/1419140\/PREDATOR","bnetURL":"http:\/\/eu.battle.net\/sc2\/en\/profile\/1419140\/1\/PREDATOR\/"},{"race":"protoss","name":"OniLink","region":"EU","url":"http:\/\/www.sc2ranks.com\/eu\/1095810\/OniLink","bnetURL":"http:\/\/eu.battle.net\/sc2\/en\/profile\/1095810\/1\/OniLink\/"}],"division":{"points":591,"wins":41,"league":"platinum","region":"EU"},"rank":1},{"players":[{"race":"protoss","name":"TheRaiven","region":"EU","url":"http:\/\/www.sc2ranks.com\/eu\/2818403\/TheRaiven","bnetURL":"http:\/\/eu.battle.net\/sc2\/en\/profile\/2818403\/1\/TheRaiven\/"},{"race":"zerg","name":"Geezzer","region":"EU","url":"http:\/\/www.sc2ranks.com\/eu\/2066050\/Geezzer","bnetURL":"http:\/\/eu.battle.net\/sc2\/en\/profile\/2066050\/1\/Geezzer\/"}],"division":{"points":591,"wins":28,"league":"platinum","region":"EU"},"rank":2},{"players":[{"race":"zerg","name":"Malchom","region":"AM","url":"http:\/\/www.sc2ranks.com\/us\/639439\/Malchom","bnetURL":"http:\/\/us.battle.net\/sc2\/en\/profile\/639439\/1\/Malchom\/"},{"race":"protoss","name":"Earthweaver","region":"AM","url":"http:\/\/www.sc2ranks.com\/us\/552620\/Earthweaver","bnetURL":"http:\/\/us.battle.net\/sc2\/en\/profile\/552620\/1\/Earthweaver\/"}],"division":{"points":587,"wins":26,"league":"platinum","region":"AM"},"rank":3},{"players":[{"race":"zerg","name":"Vader","region":"AM","url":"http:\/\/www.sc2ranks.com\/us\/2296820\/Vader","bnetURL":"http:\/\/us.battle.net\/sc2\/en\/profile\/2296820\/1\/Vader\/"},{"race":"terran","name":"KatyMyPerry","region":"AM","url":"http:\/\/www.sc2ranks.com\/us\/2483993\/KatyMyPerry","bnetURL":"http:\/\/us.battle.net\/sc2\/en\/profile\/2483993\/1\/KatyMyPerry\/"}],"division":{"points":565,"wins":38,"league":"platinum","region":"AM"},"rank":4},{"players":[{"race":"terran","name":"XoKz","region":"AM","url":"http:\/\/www.sc2ranks.com\/us\/290372\/XoKz","bnetURL":"http:\/\/us.battle.net\/sc2\/en\/profile\/290372\/1\/XoKz\/"},{"race":"zerg","name":"RecLuDe","region":"AM","url":"http:\/\/www.sc2ranks.com\/us\/989775\/RecLuDe","bnetURL":"http:\/\/us.battle.net\/sc2\/en\/profile\/989775\/1\/RecLuDe\/"}],"division":{"points":564,"wins":32,"league":"platinum","region":"AM"},"rank":5},{"players":[{"race":"zerg","name":"RageZerg","region":"EU","url":"http:\/\/www.sc2ranks.com\/eu\/2132402\/RageZerg","bnetURL":"http:\/\/eu.battle.net\/sc2\/en\/profile\/2132402\/1\/RageZerg\/"},{"race":"terran","name":"Alibambam","region":"EU","url":"http:\/\/www.sc2ranks.com\/eu\/2407090\/Alibambam","bnetURL":"http:\/\/eu.battle.net\/sc2\/en\/profile\/2407090\/1\/Alibambam\/"}],"division":{"points":556,"wins":30,"league":"platinum","region":"EU"},"rank":6},{"players":[{"race":"protoss","name":"SiGFRi","region":"AM","url":"http:\/\/www.sc2ranks.com\/us\/1968874\/SiGFRi","bnetURL":"http:\/\/us.battle.net\/sc2\/en\/profile\/1968874\/1\/SiGFRi\/"},{"race":"protoss","name":"BloOdSquad","region":"AM","url":"http:\/\/www.sc2ranks.com\/us\/2862857\/BloOdSquad","bnetURL":"http:\/\/us.battle.net\/sc2\/en\/profile\/2862857\/1\/BloOdSquad\/"}],"division":{"points":551,"wins":36,"league":"platinum","region":"AM"},"rank":7},{"players":[{"race":"random","name":"dwb","region":"EU","url":"http:\/\/www.sc2ranks.com\/eu\/982979\/dwb","bnetURL":"http:\/\/eu.battle.net\/sc2\/en\/profile\/982979\/1\/dwb\/"},{"race":"random","name":"Gorby","region":"EU","url":"http:\/\/www.sc2ranks.com\/eu\/281983\/Gorby","bnetURL":"http:\/\/eu.battle.net\/sc2\/en\/profile\/281983\/1\/Gorby\/"}],"division":{"points":550,"wins":48,"league":"platinum","region":"EU"},"rank":8},{"players":[{"race":"terran","name":"SSNInGa","region":"AM","url":"http:\/\/www.sc2ranks.com\/us\/1355071\/SSNInGa","bnetURL":"http:\/\/us.battle.net\/sc2\/en\/profile\/1355071\/1\/SSNInGa\/"},{"race":"terran","name":"SSNSmashKAB","region":"AM","url":"http:\/\/www.sc2ranks.com\/us\/323860\/SSNSmashKAB","bnetURL":"http:\/\/us.battle.net\/sc2\/en\/profile\/323860\/1\/SSNSmashKAB\/"}],"division":{"points":546,"wins":31,"league":"platinum","region":"AM"},"rank":9},{"players":[{"race":"zerg","name":"SotuRi","region":"EU","url":"http:\/\/www.sc2ranks.com\/eu\/1212658\/SotuRi","bnetURL":"http:\/\/eu.battle.net\/sc2\/en\/profile\/1212658\/1\/SotuRi\/"},{"race":"zerg","name":"sPawningPOOP","region":"EU","url":"http:\/\/www.sc2ranks.com\/eu\/1381277\/sPawningPOOP","bnetURL":"http:\/\/eu.battle.net\/sc2\/en\/profile\/1381277\/1\/sPawningPOOP\/"}],"division":{"points":534,"wins":21,"league":"platinum","region":"EU"},"rank":10},{"players":[{"race":"terran","name":"Riky","region":"EU","url":"http:\/\/www.sc2ranks.com\/eu\/732893\/Riky","bnetURL":"http:\/\/eu.battle.net\/sc2\/en\/profile\/732893\/1\/Riky\/"},{"race":"protoss","name":"pipienko","region":"EU","url":"http:\/\/www.sc2ranks.com\/eu\/1376790\/pipienko","bnetURL":"http:\/\/eu.battle.net\/sc2\/en\/profile\/1376790\/1\/pipienko\/"}],"division":{"points":525,"wins":22,"league":"platinum","region":"EU"},"rank":11},{"players":[{"race":"protoss","name":"Mozqito","region":"EU","url":"http:\/\/www.sc2ranks.com\/eu\/1383217\/Mozqito","bnetURL":"http:\/\/eu.battle.net\/sc2\/en\/profile\/1383217\/1\/Mozqito\/"},{"race":"protoss","name":"YoWoNe","region":"EU","url":"http:\/\/www.sc2ranks.com\/eu\/632233\/YoWoNe","bnetURL":"http:\/\/eu.battle.net\/sc2\/en\/profile\/632233\/1\/YoWoNe\/"}],"division":{"points":524,"wins":69,"league":"platinum","region":"EU"},"rank":12},{"players":[{"race":"protoss","name":"Angstypoo","region":"AM","url":"http:\/\/www.sc2ranks.com\/us\/2781895\/Angstypoo","bnetURL":"http:\/\/us.battle.net\/sc2\/en\/profile\/2781895\/1\/Angstypoo\/"},{"race":"protoss","name":"kentofighter","region":"AM","url":"http:\/\/www.sc2ranks.com\/us\/1091134\/kentofighter","bnetURL":"http:\/\/us.battle.net\/sc2\/en\/profile\/1091134\/1\/kentofighter\/"}],"division":{"points":515,"wins":25,"league":"platinum","region":"AM"},"rank":13},{"players":[{"race":"zerg","name":"CrazyKing","region":"AM","url":"http:\/\/www.sc2ranks.com\/us\/1965404\/CrazyKing","bnetURL":"http:\/\/us.battle.net\/sc2\/en\/profile\/1965404\/1\/CrazyKing\/"},{"race":"zerg","name":"RavenNova","region":"AM","url":"http:\/\/www.sc2ranks.com\/us\/886959\/RavenNova","bnetURL":"http:\/\/us.battle.net\/sc2\/en\/profile\/886959\/1\/RavenNova\/"}],"division":{"points":514,"wins":83,"league":"platinum","region":"AM"},"rank":14},{"players":[{"race":"protoss","name":"Sevres","region":"EU","url":"http:\/\/www.sc2ranks.com\/eu\/1748600\/Sevres","bnetURL":"http:\/\/eu.battle.net\/sc2\/en\/profile\/1748600\/1\/Sevres\/"},{"race":"random","name":"Melo","region":"EU","url":"http:\/\/www.sc2ranks.com\/eu\/1705658\/Melo","bnetURL":"http:\/\/eu.battle.net\/sc2\/en\/profile\/1705658\/1\/Melo\/"}],"division":{"points":514,"wins":33,"league":"platinum","region":"EU"},"rank":15},{"players":[{"race":"protoss","name":"oscarjames","region":"EU","url":"http:\/\/www.sc2ranks.com\/eu\/1203045\/oscarjames","bnetURL":"http:\/\/eu.battle.net\/sc2\/en\/profile\/1203045\/1\/oscarjames\/"},{"race":"random","name":"NfteamKakaoo","region":"EU","url":"http:\/\/www.sc2ranks.com\/eu\/181400\/NfteamKakaoo","bnetURL":"http:\/\/eu.battle.net\/sc2\/en\/profile\/181400\/1\/NfteamKakaoo\/"}],"division":{"points":513,"wins":53,"league":"platinum","region":"EU"},"rank":16},{"players":[{"race":"protoss","name":"Zen","region":"AM","url":"http:\/\/www.sc2ranks.com\/us\/1594513\/Zen","bnetURL":"http:\/\/us.battle.net\/sc2\/en\/profile\/1594513\/1\/Zen\/"},{"race":"terran","name":"FireInRain","region":"AM","url":"http:\/\/www.sc2ranks.com\/us\/1656195\/FireInRain","bnetURL":"http:\/\/us.battle.net\/sc2\/en\/profile\/1656195\/1\/FireInRain\/"}],"division":{"points":511,"wins":21,"league":"platinum","region":"AM"},"rank":17},{"players":[{"race":"protoss","name":"Ben","region":"EU","url":"http:\/\/www.sc2ranks.com\/eu\/1477443\/Ben","bnetURL":"http:\/\/eu.battle.net\/sc2\/en\/profile\/1477443\/1\/Ben\/"},{"race":"terran","name":"Shmokin","region":"EU","url":"http:\/\/www.sc2ranks.com\/eu\/2328531\/Shmokin","bnetURL":"http:\/\/eu.battle.net\/sc2\/en\/profile\/2328531\/1\/Shmokin\/"}],"division":{"points":510,"wins":44,"league":"platinum","region":"EU"},"rank":18},{"players":[{"race":"zerg","name":"Pineapples","region":"AM","url":"http:\/\/www.sc2ranks.com\/us\/2399807\/Pineapples","bnetURL":"http:\/\/us.battle.net\/sc2\/en\/profile\/2399807\/1\/Pineapples\/"},{"race":"terran","name":"Covalent","region":"AM","url":"http:\/\/www.sc2ranks.com\/us\/2320595\/Covalent","bnetURL":"http:\/\/us.battle.net\/sc2\/en\/profile\/2320595\/1\/Covalent\/"}],"division":{"points":508,"wins":29,"league":"platinum","region":"AM"},"rank":19},{"players":[{"race":"protoss","name":"blueandrew","region":"AM","url":"http:\/\/www.sc2ranks.com\/us\/2842816\/blueandrew","bnetURL":"http:\/\/us.battle.net\/sc2\/en\/profile\/2842816\/1\/blueandrew\/"},{"race":"zerg","name":"iliveincoto","region":"AM","url":"http:\/\/www.sc2ranks.com\/us\/534956\/iliveincoto","bnetURL":"http:\/\/us.battle.net\/sc2\/en\/profile\/534956\/1\/iliveincoto\/"}],"division":{"points":506,"wins":22,"league":"platinum","region":"AM"},"rank":20},{"players":[{"race":"protoss","name":"Deutz","region":"EU","url":"http:\/\/www.sc2ranks.com\/eu\/2900761\/Deutz","bnetURL":"http:\/\/eu.battle.net\/sc2\/en\/profile\/2900761\/1\/Deutz\/"},{"race":"terran","name":"BUZZ","region":"EU","url":"http:\/\/www.sc2ranks.com\/eu\/907382\/BUZZ","bnetURL":"http:\/\/eu.battle.net\/sc2\/en\/profile\/907382\/1\/BUZZ\/"}],"division":{"points":505,"wins":35,"league":"platinum","region":"EU"},"rank":21},{"players":[{"race":"protoss","name":"SeikO","region":"EU","url":"http:\/\/www.sc2ranks.com\/eu\/2584943\/SeikO","bnetURL":"http:\/\/eu.battle.net\/sc2\/en\/profile\/2584943\/1\/SeikO\/"},{"race":"zerg","name":"Pegeyaime","region":"EU","url":"http:\/\/www.sc2ranks.com\/eu\/2701324\/Pegeyaime","bnetURL":"http:\/\/eu.battle.net\/sc2\/en\/profile\/2701324\/1\/Pegeyaime\/"}],"division":{"points":505,"wins":32,"league":"platinum","region":"EU"},"rank":22},{"players":[{"race":"protoss","name":"Brohemoth","region":"AM","url":"http:\/\/www.sc2ranks.com\/us\/1993161\/Brohemoth","bnetURL":"http:\/\/us.battle.net\/sc2\/en\/profile\/1993161\/1\/Brohemoth\/"},{"race":"zerg","name":"woople","region":"AM","url":"http:\/\/www.sc2ranks.com\/us\/304922\/woople","bnetURL":"http:\/\/us.battle.net\/sc2\/en\/profile\/304922\/1\/woople\/"}],"division":{"points":503,"wins":28,"league":"platinum","region":"AM"},"rank":23},{"players":[{"race":"zerg","name":"jqpeub","region":"AM","url":"http:\/\/www.sc2ranks.com\/us\/2620766\/jqpeub","bnetURL":"http:\/\/us.battle.net\/sc2\/en\/profile\/2620766\/1\/jqpeub\/"},{"race":"terran","name":"Spladow","region":"AM","url":"http:\/\/www.sc2ranks.com\/us\/1025553\/Spladow","bnetURL":"http:\/\/us.battle.net\/sc2\/en\/profile\/1025553\/1\/Spladow\/"}],"division":{"points":502,"wins":95,"league":"platinum","region":"AM"},"rank":24},{"players":[{"race":"zerg","name":"Celadon","region":"AM","url":"http:\/\/www.sc2ranks.com\/us\/345587\/Celadon","bnetURL":"http:\/\/us.battle.net\/sc2\/en\/profile\/345587\/1\/Celadon\/"},{"race":"terran","name":"Frothlobster","region":"AM","url":"http:\/\/www.sc2ranks.com\/us\/2348365\/Frothlobster","bnetURL":"http:\/\/us.battle.net\/sc2\/en\/profile\/2348365\/1\/Frothlobster\/"}],"division":{"points":501,"wins":39,"league":"platinum","region":"AM"},"rank":25},{"players":[{"race":"terran","name":"HAL","region":"AM","url":"http:\/\/www.sc2ranks.com\/us\/2615932\/HAL","bnetURL":"http:\/\/us.battle.net\/sc2\/en\/profile\/2615932\/1\/HAL\/"},{"race":"zerg","name":"Paperboat","region":"AM","url":"http:\/\/www.sc2ranks.com\/us\/2614992\/Paperboat","bnetURL":"http:\/\/us.battle.net\/sc2\/en\/profile\/2614992\/1\/Paperboat\/"}],"division":{"points":501,"wins":38,"league":"platinum","region":"AM"},"rank":26},{"players":[{"race":"protoss","name":"Clark","region":"EU","url":"http:\/\/www.sc2ranks.com\/ru\/655036\/Clark","bnetURL":"http:\/\/eu.battle.net\/sc2\/en\/profile\/655036\/2\/Clark\/"},{"race":"zerg","name":"Aleksandr","region":"EU","url":"http:\/\/www.sc2ranks.com\/ru\/326963\/Aleksandr","bnetURL":"http:\/\/eu.battle.net\/sc2\/en\/profile\/326963\/2\/Aleksandr\/"}],"division":{"points":498,"wins":49,"league":"platinum","region":"EU"},"rank":27},{"players":[{"race":"zerg","name":"nitroX","region":"EU","url":"http:\/\/www.sc2ranks.com\/eu\/1308473\/nitroX","bnetURL":"http:\/\/eu.battle.net\/sc2\/en\/profile\/1308473\/1\/nitroX\/"},{"race":"protoss","name":"Nighty","region":"EU","url":"http:\/\/www.sc2ranks.com\/eu\/1226344\/Nighty","bnetURL":"http:\/\/eu.battle.net\/sc2\/en\/profile\/1226344\/1\/Nighty\/"}],"division":{"points":496,"wins":48,"league":"platinum","region":"EU"},"rank":28},{"players":[{"race":"zerg","name":"Zurako","region":"AM","url":"http:\/\/www.sc2ranks.com\/us\/630470\/Zurako","bnetURL":"http:\/\/us.battle.net\/sc2\/en\/profile\/630470\/1\/Zurako\/"},{"race":"protoss","name":"Quasar","region":"AM","url":"http:\/\/www.sc2ranks.com\/us\/3310710\/Quasar","bnetURL":"http:\/\/us.battle.net\/sc2\/en\/profile\/3310710\/1\/Quasar\/"}],"division":{"points":495,"wins":31,"league":"platinum","region":"AM"},"rank":29},{"players":[{"race":"protoss","name":"Stripped","region":"CN","url":"http:\/\/www.sc2ranks.com\/cn\/1372368\/Stripped","bnetURL":"http:\/\/www.battlenet.com.cn\/sc2\/zh\/profile\/1372368\/1\/Stripped\/"},{"race":"zerg","name":"\u897f\u5357\u8d22\u7ecf\u5927\u5b66","region":"CN","url":"http:\/\/www.sc2ranks.com\/cn\/2103319\/%E8%A5%BF%E5%8D%97%E8%B4%A2%E7%BB%8F%E5%A4%A7%E5%AD%A6","bnetURL":"http:\/\/www.battlenet.com.cn\/sc2\/zh\/profile\/2103319\/1\/%E8%A5%BF%E5%8D%97%E8%B4%A2%E7%BB%8F%E5%A4%A7%E5%AD%A6\/"}],"division":{"points":495,"wins":24,"league":"platinum","region":"CN"},"rank":30},{"players":[{"race":"terran","name":"JustGodlike","region":"EU","url":"http:\/\/www.sc2ranks.com\/eu\/1828502\/JustGodlike","bnetURL":"http:\/\/eu.battle.net\/sc2\/en\/profile\/1828502\/1\/JustGodlike\/"},{"race":"zerg","name":"Mars","region":"EU","url":"http:\/\/www.sc2ranks.com\/eu\/2542212\/Mars","bnetURL":"http:\/\/eu.battle.net\/sc2\/en\/profile\/2542212\/1\/Mars\/"}],"division":{"points":494,"wins":36,"league":"platinum","region":"EU"},"rank":31},{"players":[{"race":"terran","name":"MagicHades","region":"CN","url":"http:\/\/www.sc2ranks.com\/cn\/543216\/MagicHades","bnetURL":"http:\/\/www.battlenet.com.cn\/sc2\/zh\/profile\/543216\/1\/MagicHades\/"},{"race":"protoss","name":"MagicAirica","region":"CN","url":"http:\/\/www.sc2ranks.com\/cn\/689071\/MagicAirica","bnetURL":"http:\/\/www.battlenet.com.cn\/sc2\/zh\/profile\/689071\/1\/MagicAirica\/"}],"division":{"points":491,"wins":83,"league":"platinum","region":"CN"},"rank":32},{"players":[{"race":"protoss","name":"oliver","region":"AM","url":"http:\/\/www.sc2ranks.com\/us\/2779603\/oliver","bnetURL":"http:\/\/us.battle.net\/sc2\/en\/profile\/2779603\/1\/oliver\/"},{"race":"random","name":"can","region":"AM","url":"http:\/\/www.sc2ranks.com\/us\/3026315\/can","bnetURL":"http:\/\/us.battle.net\/sc2\/en\/profile\/3026315\/1\/can\/"}],"division":{"points":491,"wins":51,"league":"platinum","region":"AM"},"rank":33},{"players":[{"race":"zerg","name":"sAviOr","region":"EU","url":"http:\/\/www.sc2ranks.com\/ru\/244524\/sAviOr","bnetURL":"http:\/\/eu.battle.net\/sc2\/en\/profile\/244524\/2\/sAviOr\/"},{"race":"protoss","name":"Alexinho","region":"EU","url":"http:\/\/www.sc2ranks.com\/eu\/2855020\/Alexinho","bnetURL":"http:\/\/eu.battle.net\/sc2\/en\/profile\/2855020\/1\/Alexinho\/"}],"division":{"points":491,"wins":20,"league":"platinum","region":"EU"},"rank":34},{"players":[{"race":"random","name":"AvengingSynd","region":"AM","url":"http:\/\/www.sc2ranks.com\/us\/2945437\/AvengingSynd","bnetURL":"http:\/\/us.battle.net\/sc2\/en\/profile\/2945437\/1\/AvengingSynd\/"},{"race":"random","name":"aprea","region":"AM","url":"http:\/\/www.sc2ranks.com\/us\/2335504\/aprea","bnetURL":"http:\/\/us.battle.net\/sc2\/en\/profile\/2335504\/1\/aprea\/"}],"division":{"points":489,"wins":41,"league":"platinum","region":"AM"},"rank":35},{"players":[{"race":"random","name":"Existence","region":"AM","url":"http:\/\/www.sc2ranks.com\/us\/1750818\/Existence","bnetURL":"http:\/\/us.battle.net\/sc2\/en\/profile\/1750818\/1\/Existence\/"},{"race":"protoss","name":"CallMeMVP","region":"AM","url":"http:\/\/www.sc2ranks.com\/us\/1629895\/CallMeMVP","bnetURL":"http:\/\/us.battle.net\/sc2\/en\/profile\/1629895\/1\/CallMeMVP\/"}],"division":{"points":488,"wins":28,"league":"platinum","region":"AM"},"rank":36},{"players":[{"race":"protoss","name":"Granets","region":"EU","url":"http:\/\/www.sc2ranks.com\/eu\/1230471\/Granets","bnetURL":"http:\/\/eu.battle.net\/sc2\/en\/profile\/1230471\/1\/Granets\/"},{"race":"random","name":"DDiCki","region":"EU","url":"http:\/\/www.sc2ranks.com\/eu\/237938\/DDiCki","bnetURL":"http:\/\/eu.battle.net\/sc2\/en\/profile\/237938\/1\/DDiCki\/"}],"division":{"points":487,"wins":24,"league":"platinum","region":"EU"},"rank":37},{"players":[{"race":"protoss","name":"Kilam","region":"AM","url":"http:\/\/www.sc2ranks.com\/us\/870623\/Kilam","bnetURL":"http:\/\/us.battle.net\/sc2\/en\/profile\/870623\/1\/Kilam\/"},{"race":"random","name":"bonkerz","region":"AM","url":"http:\/\/www.sc2ranks.com\/us\/1535502\/bonkerz","bnetURL":"http:\/\/us.battle.net\/sc2\/en\/profile\/1535502\/1\/bonkerz\/"}],"division":{"points":485,"wins":46,"league":"platinum","region":"AM"},"rank":38},{"players":[{"race":"protoss","name":"\uc6d0\ud560\uba38\ub2c8\ubcf4\uace0\uc308","region":"KR&TW","url":"http:\/\/www.sc2ranks.com\/kr\/3619140\/%EC%9B%90%ED%95%A0%EB%A8%B8%EB%8B%88%EB%B3%B4%EA%B3%A0%EC%8C%88","bnetURL":"http:\/\/kr.battle.net\/sc2\/ko\/profile\/3619140\/1\/%EC%9B%90%ED%95%A0%EB%A8%B8%EB%8B%88%EB%B3%B4%EA%B3%A0%EC%8C%88\/"},{"race":"zerg","name":"RedChocolate","region":"KR&TW","url":"http:\/\/www.sc2ranks.com\/kr\/3930717\/RedChocolate","bnetURL":"http:\/\/kr.battle.net\/sc2\/ko\/profile\/3930717\/1\/RedChocolate\/"}],"division":{"points":485,"wins":28,"league":"platinum","region":"KR&TW"},"rank":39},{"players":[{"race":"terran","name":"xoxTobiasxox","region":"EU","url":"http:\/\/www.sc2ranks.com\/eu\/2358265\/xoxTobiasxox","bnetURL":"http:\/\/eu.battle.net\/sc2\/en\/profile\/2358265\/1\/xoxTobiasxox\/"},{"race":"terran","name":"Salvation","region":"EU","url":"http:\/\/www.sc2ranks.com\/eu\/1625445\/Salvation","bnetURL":"http:\/\/eu.battle.net\/sc2\/en\/profile\/1625445\/1\/Salvation\/"}],"division":{"points":484,"wins":34,"league":"platinum","region":"EU"},"rank":40},{"players":[{"race":"terran","name":"ChangChongAh","region":"AM","url":"http:\/\/www.sc2ranks.com\/us\/1520871\/ChangChongAh","bnetURL":"http:\/\/us.battle.net\/sc2\/en\/profile\/1520871\/1\/ChangChongAh\/"},{"race":"terran","name":"Freeze","region":"AM","url":"http:\/\/www.sc2ranks.com\/us\/3241229\/Freeze","bnetURL":"http:\/\/us.battle.net\/sc2\/en\/profile\/3241229\/1\/Freeze\/"}],"division":{"points":484,"wins":26,"league":"platinum","region":"AM"},"rank":41},{"players":[{"race":"terran","name":"\u5ba2\u5b98\u4e0d\u53ef\u4ee5","region":"CN","url":"http:\/\/www.sc2ranks.com\/cn\/1742452\/%E5%AE%A2%E5%AE%98%E4%B8%8D%E5%8F%AF%E4%BB%A5","bnetURL":"http:\/\/www.battlenet.com.cn\/sc2\/zh\/profile\/1742452\/1\/%E5%AE%A2%E5%AE%98%E4%B8%8D%E5%8F%AF%E4%BB%A5\/"},{"race":"zerg","name":"\u7537\u5b69\u50cf\u59b3","region":"CN","url":"http:\/\/www.sc2ranks.com\/cn\/1740349\/%E7%94%B7%E5%AD%A9%E5%83%8F%E5%A6%B3","bnetURL":"http:\/\/www.battlenet.com.cn\/sc2\/zh\/profile\/1740349\/1\/%E7%94%B7%E5%AD%A9%E5%83%8F%E5%A6%B3\/"}],"division":{"points":484,"wins":16,"league":"platinum","region":"CN"},"rank":42},{"players":[{"race":"terran","name":"Marine","region":"KR&TW","url":"http:\/\/www.sc2ranks.com\/kr\/1597654\/Marine","bnetURL":"http:\/\/kr.battle.net\/sc2\/ko\/profile\/1597654\/1\/Marine\/"},{"race":"random","name":"\ud55c\uad6d\uc758\ubbf8","region":"KR&TW","url":"http:\/\/www.sc2ranks.com\/kr\/1398544\/%ED%95%9C%EA%B5%AD%EC%9D%98%EB%AF%B8","bnetURL":"http:\/\/kr.battle.net\/sc2\/ko\/profile\/1398544\/1\/%ED%95%9C%EA%B5%AD%EC%9D%98%EB%AF%B8\/"}],"division":{"points":483,"wins":56,"league":"platinum","region":"KR&TW"},"rank":43},{"players":[{"race":"protoss","name":"\ucef4\ud4e8\ud130","region":"KR&TW","url":"http:\/\/www.sc2ranks.com\/kr\/2574149\/%EC%BB%B4%ED%93%A8%ED%84%B0","bnetURL":"http:\/\/kr.battle.net\/sc2\/ko\/profile\/2574149\/1\/%EC%BB%B4%ED%93%A8%ED%84%B0\/"},{"race":"terran","name":"KBS","region":"KR&TW","url":"http:\/\/www.sc2ranks.com\/kr\/2000426\/KBS","bnetURL":"http:\/\/kr.battle.net\/sc2\/ko\/profile\/2000426\/1\/KBS\/"}],"division":{"points":482,"wins":38,"league":"platinum","region":"KR&TW"},"rank":44},{"players":[{"race":"zerg","name":"RayLovJunBao","region":"AM","url":"http:\/\/www.sc2ranks.com\/us\/2819677\/RayLovJunBao","bnetURL":"http:\/\/us.battle.net\/sc2\/en\/profile\/2819677\/1\/RayLovJunBao\/"},{"race":"terran","name":"RedDevil","region":"AM","url":"http:\/\/www.sc2ranks.com\/us\/2788478\/RedDevil","bnetURL":"http:\/\/us.battle.net\/sc2\/en\/profile\/2788478\/1\/RedDevil\/"}],"division":{"points":482,"wins":35,"league":"platinum","region":"AM"},"rank":45},{"players":[{"race":"zerg","name":"SomeLink","region":"AM","url":"http:\/\/www.sc2ranks.com\/us\/491246\/SomeLink","bnetURL":"http:\/\/us.battle.net\/sc2\/en\/profile\/491246\/1\/SomeLink\/"},{"race":"protoss","name":"DEADkGoR","region":"AM","url":"http:\/\/www.sc2ranks.com\/us\/940481\/DEADkGoR","bnetURL":"http:\/\/us.battle.net\/sc2\/en\/profile\/940481\/1\/DEADkGoR\/"}],"division":{"points":482,"wins":29,"league":"platinum","region":"AM"},"rank":46},{"players":[{"race":"terran","name":"Aotomatic","region":"CN","url":"http:\/\/www.sc2ranks.com\/cn\/2155024\/Aotomatic","bnetURL":"http:\/\/www.battlenet.com.cn\/sc2\/zh\/profile\/2155024\/1\/Aotomatic\/"},{"race":"protoss","name":"Samael","region":"CN","url":"http:\/\/www.sc2ranks.com\/cn\/312124\/Samael","bnetURL":"http:\/\/www.battlenet.com.cn\/sc2\/zh\/profile\/312124\/1\/Samael\/"}],"division":{"points":482,"wins":25,"league":"platinum","region":"CN"},"rank":47},{"players":[{"race":"zerg","name":"sevensAZ","region":"AM","url":"http:\/\/www.sc2ranks.com\/us\/379113\/sevensAZ","bnetURL":"http:\/\/us.battle.net\/sc2\/en\/profile\/379113\/1\/sevensAZ\/"},{"race":"protoss","name":"NicolasRage","region":"AM","url":"http:\/\/www.sc2ranks.com\/us\/365220\/NicolasRage","bnetURL":"http:\/\/us.battle.net\/sc2\/en\/profile\/365220\/1\/NicolasRage\/"}],"division":{"points":481,"wins":31,"league":"platinum","region":"AM"},"rank":48},{"players":[{"race":"protoss","name":"Malem","region":"AM","url":"http:\/\/www.sc2ranks.com\/us\/1734671\/Malem","bnetURL":"http:\/\/us.battle.net\/sc2\/en\/profile\/1734671\/1\/Malem\/"},{"race":"zerg","name":"nbrave","region":"AM","url":"http:\/\/www.sc2ranks.com\/us\/1574062\/nbrave","bnetURL":"http:\/\/us.battle.net\/sc2\/en\/profile\/1574062\/1\/nbrave\/"}],"division":{"points":480,"wins":71,"league":"platinum","region":"AM"},"rank":49},{"players":[{"race":"protoss","name":"brenman","region":"AM","url":"http:\/\/www.sc2ranks.com\/us\/3436282\/brenman","bnetURL":"http:\/\/us.battle.net\/sc2\/en\/profile\/3436282\/1\/brenman\/"},{"race":"protoss","name":"FrantiK","region":"AM","url":"http:\/\/www.sc2ranks.com\/us\/2309225\/FrantiK","bnetURL":"http:\/\/us.battle.net\/sc2\/en\/profile\/2309225\/1\/FrantiK\/"}],"division":{"points":480,"wins":54,"league":"platinum","region":"AM"},"rank":50},{"players":[{"race":"terran","name":"Phrance","region":"AM","url":"http:\/\/www.sc2ranks.com\/us\/3348510\/Phrance","bnetURL":"http:\/\/us.battle.net\/sc2\/en\/profile\/3348510\/1\/Phrance\/"},{"race":"protoss","name":"Cysote","region":"AM","url":"http:\/\/www.sc2ranks.com\/us\/834638\/Cysote","bnetURL":"http:\/\/us.battle.net\/sc2\/en\/profile\/834638\/1\/Cysote\/"}],"division":{"points":480,"wins":31,"league":"platinum","region":"AM"},"rank":51},{"players":[{"race":"zerg","name":"Syrianto","region":"AM","url":"http:\/\/www.sc2ranks.com\/us\/1758110\/Syrianto","bnetURL":"http:\/\/us.battle.net\/sc2\/en\/profile\/1758110\/1\/Syrianto\/"},{"race":"protoss","name":"EZToDaMax","region":"AM","url":"http:\/\/www.sc2ranks.com\/us\/3348133\/EZToDaMax","bnetURL":"http:\/\/us.battle.net\/sc2\/en\/profile\/3348133\/1\/EZToDaMax\/"}],"division":{"points":480,"wins":24,"league":"platinum","region":"AM"},"rank":52},{"players":[{"race":"zerg","name":"Phoru","region":"EU","url":"http:\/\/www.sc2ranks.com\/eu\/750376\/Phoru","bnetURL":"http:\/\/eu.battle.net\/sc2\/en\/profile\/750376\/1\/Phoru\/"},{"race":"protoss","name":"Sheltz","region":"EU","url":"http:\/\/www.sc2ranks.com\/eu\/1665644\/Sheltz","bnetURL":"http:\/\/eu.battle.net\/sc2\/en\/profile\/1665644\/1\/Sheltz\/"}],"division":{"points":479,"wins":99,"league":"platinum","region":"EU"},"rank":53},{"players":[{"race":"zerg","name":"WEdouard","region":"EU","url":"http:\/\/www.sc2ranks.com\/eu\/2047606\/WEdouard","bnetURL":"http:\/\/eu.battle.net\/sc2\/en\/profile\/2047606\/1\/WEdouard\/"},{"race":"zerg","name":"Kukulkan","region":"EU","url":"http:\/\/www.sc2ranks.com\/eu\/2046935\/Kukulkan","bnetURL":"http:\/\/eu.battle.net\/sc2\/en\/profile\/2046935\/1\/Kukulkan\/"}],"division":{"points":478,"wins":72,"league":"platinum","region":"EU"},"rank":54},{"players":[{"race":"random","name":"NaiveSkull","region":"AM","url":"http:\/\/www.sc2ranks.com\/us\/877060\/NaiveSkull","bnetURL":"http:\/\/us.battle.net\/sc2\/en\/profile\/877060\/1\/NaiveSkull\/"},{"race":"random","name":"Kreator","region":"AM","url":"http:\/\/www.sc2ranks.com\/us\/2947882\/Kreator","bnetURL":"http:\/\/us.battle.net\/sc2\/en\/profile\/2947882\/1\/Kreator\/"}],"division":{"points":478,"wins":37,"league":"platinum","region":"AM"},"rank":55},{"players":[{"race":"terran","name":"Ghost","region":"AM","url":"http:\/\/www.sc2ranks.com\/us\/1925893\/Ghost","bnetURL":"http:\/\/us.battle.net\/sc2\/en\/profile\/1925893\/1\/Ghost\/"},{"race":"terran","name":"BooYa","region":"AM","url":"http:\/\/www.sc2ranks.com\/us\/2120929\/BooYa","bnetURL":"http:\/\/us.battle.net\/sc2\/en\/profile\/2120929\/1\/BooYa\/"}],"division":{"points":477,"wins":61,"league":"platinum","region":"AM"},"rank":56},{"players":[{"race":"protoss","name":"Shadow","region":"AM","url":"http:\/\/www.sc2ranks.com\/us\/3749276\/Shadow","bnetURL":"http:\/\/us.battle.net\/sc2\/en\/profile\/3749276\/1\/Shadow\/"},{"race":"zerg","name":"InVicTuS","region":"AM","url":"http:\/\/www.sc2ranks.com\/us\/3107664\/InVicTuS","bnetURL":"http:\/\/us.battle.net\/sc2\/en\/profile\/3107664\/1\/InVicTuS\/"}],"division":{"points":476,"wins":46,"league":"platinum","region":"AM"},"rank":57},{"players":[{"race":"terran","name":"THEdoorknob","region":"AM","url":"http:\/\/www.sc2ranks.com\/us\/2208420\/THEdoorknob","bnetURL":"http:\/\/us.battle.net\/sc2\/en\/profile\/2208420\/1\/THEdoorknob\/"},{"race":"protoss","name":"Whitelancer","region":"AM","url":"http:\/\/www.sc2ranks.com\/us\/2030073\/Whitelancer","bnetURL":"http:\/\/us.battle.net\/sc2\/en\/profile\/2030073\/1\/Whitelancer\/"}],"division":{"points":476,"wins":31,"league":"platinum","region":"AM"},"rank":58},{"players":[{"race":"zerg","name":"Polemarch","region":"AM","url":"http:\/\/www.sc2ranks.com\/us\/1647389\/Polemarch","bnetURL":"http:\/\/us.battle.net\/sc2\/en\/profile\/1647389\/1\/Polemarch\/"},{"race":"terran","name":"Zeuswoo","region":"AM","url":"http:\/\/www.sc2ranks.com\/us\/559611\/Zeuswoo","bnetURL":"http:\/\/us.battle.net\/sc2\/en\/profile\/559611\/1\/Zeuswoo\/"}],"division":{"points":475,"wins":28,"league":"platinum","region":"AM"},"rank":59},{"players":[{"race":"zerg","name":"Olegar","region":"EU","url":"http:\/\/www.sc2ranks.com\/eu\/726266\/Olegar","bnetURL":"http:\/\/eu.battle.net\/sc2\/en\/profile\/726266\/1\/Olegar\/"},{"race":"zerg","name":"dontpanic","region":"EU","url":"http:\/\/www.sc2ranks.com\/eu\/754605\/dontpanic","bnetURL":"http:\/\/eu.battle.net\/sc2\/en\/profile\/754605\/1\/dontpanic\/"}],"division":{"points":474,"wins":31,"league":"platinum","region":"EU"},"rank":60},{"players":[{"race":"random","name":"Gobo","region":"EU","url":"http:\/\/www.sc2ranks.com\/eu\/566960\/Gobo","bnetURL":"http:\/\/eu.battle.net\/sc2\/en\/profile\/566960\/1\/Gobo\/"},{"race":"protoss","name":"Agnostiker","region":"EU","url":"http:\/\/www.sc2ranks.com\/eu\/2075349\/Agnostiker","bnetURL":"http:\/\/eu.battle.net\/sc2\/en\/profile\/2075349\/1\/Agnostiker\/"}],"division":{"points":472,"wins":90,"league":"platinum","region":"EU"},"rank":61},{"players":[{"race":"protoss","name":"MiRo","region":"EU","url":"http:\/\/www.sc2ranks.com\/eu\/2216934\/MiRo","bnetURL":"http:\/\/eu.battle.net\/sc2\/en\/profile\/2216934\/1\/MiRo\/"},{"race":"protoss","name":"Thunder","region":"EU","url":"http:\/\/www.sc2ranks.com\/eu\/2253274\/Thunder","bnetURL":"http:\/\/eu.battle.net\/sc2\/en\/profile\/2253274\/1\/Thunder\/"}],"division":{"points":472,"wins":66,"league":"platinum","region":"EU"},"rank":62},{"players":[{"race":"terran","name":"DiMka","region":"EU","url":"http:\/\/www.sc2ranks.com\/eu\/292202\/DiMka","bnetURL":"http:\/\/eu.battle.net\/sc2\/en\/profile\/292202\/1\/DiMka\/"},{"race":"protoss","name":"Leon","region":"EU","url":"http:\/\/www.sc2ranks.com\/eu\/464556\/Leon","bnetURL":"http:\/\/eu.battle.net\/sc2\/en\/profile\/464556\/1\/Leon\/"}],"division":{"points":472,"wins":32,"league":"platinum","region":"EU"},"rank":63},{"players":[{"race":"zerg","name":"BrigaDIR","region":"EU","url":"http:\/\/www.sc2ranks.com\/eu\/1947856\/BrigaDIR","bnetURL":"http:\/\/eu.battle.net\/sc2\/en\/profile\/1947856\/1\/BrigaDIR\/"},{"race":"protoss","name":"TurboMorph","region":"EU","url":"http:\/\/www.sc2ranks.com\/eu\/1946905\/TurboMorph","bnetURL":"http:\/\/eu.battle.net\/sc2\/en\/profile\/1946905\/1\/TurboMorph\/"}],"division":{"points":471,"wins":72,"league":"platinum","region":"EU"},"rank":64},{"players":[{"race":"protoss","name":"SPANI","region":"EU","url":"http:\/\/www.sc2ranks.com\/eu\/1093180\/SPANI","bnetURL":"http:\/\/eu.battle.net\/sc2\/en\/profile\/1093180\/1\/SPANI\/"},{"race":"zerg","name":"Andyman","region":"EU","url":"http:\/\/www.sc2ranks.com\/eu\/788885\/Andyman","bnetURL":"http:\/\/eu.battle.net\/sc2\/en\/profile\/788885\/1\/Andyman\/"}],"division":{"points":471,"wins":49,"league":"platinum","region":"EU"},"rank":65},{"players":[{"race":"zerg","name":"goro","region":"EU","url":"http:\/\/www.sc2ranks.com\/eu\/2658409\/goro","bnetURL":"http:\/\/eu.battle.net\/sc2\/en\/profile\/2658409\/1\/goro\/"},{"race":"protoss","name":"yahmot","region":"EU","url":"http:\/\/www.sc2ranks.com\/eu\/2621713\/yahmot","bnetURL":"http:\/\/eu.battle.net\/sc2\/en\/profile\/2621713\/1\/yahmot\/"}],"division":{"points":471,"wins":46,"league":"platinum","region":"EU"},"rank":66},{"players":[{"race":"zerg","name":"\ub7ed\uc154\ub9ac\ud55c\uac70\uc9c0","region":"KR&TW","url":"http:\/\/www.sc2ranks.com\/kr\/2405601\/%EB%9F%AD%EC%85%94%EB%A6%AC%ED%95%9C%EA%B1%B0%EC%A7%80","bnetURL":"http:\/\/kr.battle.net\/sc2\/ko\/profile\/2405601\/1\/%EB%9F%AD%EC%85%94%EB%A6%AC%ED%95%9C%EA%B1%B0%EC%A7%80\/"},{"race":"random","name":"\uc218\uc9c0","region":"KR&TW","url":"http:\/\/www.sc2ranks.com\/kr\/2304993\/%EC%88%98%EC%A7%80","bnetURL":"http:\/\/kr.battle.net\/sc2\/ko\/profile\/2304993\/1\/%EC%88%98%EC%A7%80\/"}],"division":{"points":471,"wins":22,"league":"platinum","region":"KR&TW"},"rank":67},{"players":[{"race":"terran","name":"Brappers","region":"EU","url":"http:\/\/www.sc2ranks.com\/eu\/1907675\/Brappers","bnetURL":"http:\/\/eu.battle.net\/sc2\/en\/profile\/1907675\/1\/Brappers\/"},{"race":"zerg","name":"Holykitty","region":"EU","url":"http:\/\/www.sc2ranks.com\/eu\/2118058\/Holykitty","bnetURL":"http:\/\/eu.battle.net\/sc2\/en\/profile\/2118058\/1\/Holykitty\/"}],"division":{"points":471,"wins":21,"league":"platinum","region":"EU"},"rank":68},{"players":[{"race":"random","name":"hugotaku","region":"EU","url":"http:\/\/www.sc2ranks.com\/eu\/1912722\/hugotaku","bnetURL":"http:\/\/eu.battle.net\/sc2\/en\/profile\/1912722\/1\/hugotaku\/"},{"race":"terran","name":"guiguikiller","region":"EU","url":"http:\/\/www.sc2ranks.com\/eu\/2023880\/guiguikiller","bnetURL":"http:\/\/eu.battle.net\/sc2\/en\/profile\/2023880\/1\/guiguikiller\/"}],"division":{"points":471,"wins":21,"league":"platinum","region":"EU"},"rank":68},{"players":[{"race":"random","name":"Shinh","region":"EU","url":"http:\/\/www.sc2ranks.com\/eu\/208138\/Shinh","bnetURL":"http:\/\/eu.battle.net\/sc2\/en\/profile\/208138\/1\/Shinh\/"},{"race":"zerg","name":"DrKadaver","region":"EU","url":"http:\/\/www.sc2ranks.com\/eu\/676447\/DrKadaver","bnetURL":"http:\/\/eu.battle.net\/sc2\/en\/profile\/676447\/1\/DrKadaver\/"}],"division":{"points":470,"wins":57,"league":"platinum","region":"EU"},"rank":69},{"players":[{"race":"zerg","name":"stankystank","region":"AM","url":"http:\/\/www.sc2ranks.com\/us\/2971971\/stankystank","bnetURL":"http:\/\/us.battle.net\/sc2\/en\/profile\/2971971\/1\/stankystank\/"},{"race":"zerg","name":"TheRod","region":"AM","url":"http:\/\/www.sc2ranks.com\/us\/2272034\/TheRod","bnetURL":"http:\/\/us.battle.net\/sc2\/en\/profile\/2272034\/1\/TheRod\/"}],"division":{"points":469,"wins":35,"league":"platinum","region":"AM"},"rank":70},{"players":[{"race":"random","name":"Brovatar","region":"EU","url":"http:\/\/www.sc2ranks.com\/eu\/968948\/Brovatar","bnetURL":"http:\/\/eu.battle.net\/sc2\/en\/profile\/968948\/1\/Brovatar\/"},{"race":"random","name":"BANIA","region":"EU","url":"http:\/\/www.sc2ranks.com\/eu\/243020\/BANIA","bnetURL":"http:\/\/eu.battle.net\/sc2\/en\/profile\/243020\/1\/BANIA\/"}],"division":{"points":468,"wins":49,"league":"platinum","region":"EU"},"rank":71},{"players":[{"race":"terran","name":"EPICWIN","region":"AM","url":"http:\/\/www.sc2ranks.com\/us\/834349\/EPICWIN","bnetURL":"http:\/\/us.battle.net\/sc2\/en\/profile\/834349\/1\/EPICWIN\/"},{"race":"protoss","name":"prosPULLout","region":"AM","url":"http:\/\/www.sc2ranks.com\/us\/1293557\/prosPULLout","bnetURL":"http:\/\/us.battle.net\/sc2\/en\/profile\/1293557\/1\/prosPULLout\/"}],"division":{"points":468,"wins":47,"league":"platinum","region":"AM"},"rank":72},{"players":[{"race":"zerg","name":"RoPMac","region":"EU","url":"http:\/\/www.sc2ranks.com\/eu\/2364016\/RoPMac","bnetURL":"http:\/\/eu.battle.net\/sc2\/en\/profile\/2364016\/1\/RoPMac\/"},{"race":"terran","name":"RoPRageHerO","region":"EU","url":"http:\/\/www.sc2ranks.com\/eu\/2648370\/RoPRageHerO","bnetURL":"http:\/\/eu.battle.net\/sc2\/en\/profile\/2648370\/1\/RoPRageHerO\/"}],"division":{"points":468,"wins":38,"league":"platinum","region":"EU"},"rank":73},{"players":[{"race":"terran","name":"pinky","region":"EU","url":"http:\/\/www.sc2ranks.com\/eu\/726119\/pinky","bnetURL":"http:\/\/eu.battle.net\/sc2\/en\/profile\/726119\/1\/pinky\/"},{"race":"zerg","name":"Asurya","region":"EU","url":"http:\/\/www.sc2ranks.com\/eu\/179762\/Asurya","bnetURL":"http:\/\/eu.battle.net\/sc2\/en\/profile\/179762\/1\/Asurya\/"}],"division":{"points":467,"wins":54,"league":"platinum","region":"EU"},"rank":74},{"players":[{"race":"random","name":"Boomi","region":"EU","url":"http:\/\/www.sc2ranks.com\/ru\/24143\/Boomi","bnetURL":"http:\/\/eu.battle.net\/sc2\/en\/profile\/24143\/2\/Boomi\/"},{"race":"random","name":"RED","region":"EU","url":"http:\/\/www.sc2ranks.com\/ru\/53921\/RED","bnetURL":"http:\/\/eu.battle.net\/sc2\/en\/profile\/53921\/2\/RED\/"}],"division":{"points":467,"wins":33,"league":"platinum","region":"EU"},"rank":75},{"players":[{"race":"terran","name":"JimmyIreland","region":"EU","url":"http:\/\/www.sc2ranks.com\/eu\/2143686\/JimmyIreland","bnetURL":"http:\/\/eu.battle.net\/sc2\/en\/profile\/2143686\/1\/JimmyIreland\/"},{"race":"protoss","name":"YANKaTANK","region":"EU","url":"http:\/\/www.sc2ranks.com\/eu\/2137840\/YANKaTANK","bnetURL":"http:\/\/eu.battle.net\/sc2\/en\/profile\/2137840\/1\/YANKaTANK\/"}],"division":{"points":466,"wins":32,"league":"platinum","region":"EU"},"rank":76},{"players":[{"race":"protoss","name":"OreHLooPXiS","region":"EU","url":"http:\/\/www.sc2ranks.com\/eu\/2962327\/OreHLooPXiS","bnetURL":"http:\/\/eu.battle.net\/sc2\/en\/profile\/2962327\/1\/OreHLooPXiS\/"},{"race":"random","name":"Derp","region":"EU","url":"http:\/\/www.sc2ranks.com\/eu\/1280106\/Derp","bnetURL":"http:\/\/eu.battle.net\/sc2\/en\/profile\/1280106\/1\/Derp\/"}],"division":{"points":465,"wins":25,"league":"platinum","region":"EU"},"rank":77},{"players":[{"race":"protoss","name":"Jeff","region":"EU","url":"http:\/\/www.sc2ranks.com\/eu\/2118092\/Jeff","bnetURL":"http:\/\/eu.battle.net\/sc2\/en\/profile\/2118092\/1\/Jeff\/"},{"race":"zerg","name":"Gen\u00f8cide","region":"EU","url":"http:\/\/www.sc2ranks.com\/eu\/2116591\/Gen%C3%B8cide","bnetURL":"http:\/\/eu.battle.net\/sc2\/en\/profile\/2116591\/1\/Gen%C3%B8cide\/"}],"division":{"points":462,"wins":41,"league":"platinum","region":"EU"},"rank":78},{"players":[{"race":"protoss","name":"\u5e7b\u98ce\u732b","region":"CN","url":"http:\/\/www.sc2ranks.com\/cn\/986775\/%E5%B9%BB%E9%A3%8E%E7%8C%AB","bnetURL":"http:\/\/www.battlenet.com.cn\/sc2\/zh\/profile\/986775\/1\/%E5%B9%BB%E9%A3%8E%E7%8C%AB\/"},{"race":"zerg","name":"Demon","region":"CN","url":"http:\/\/www.sc2ranks.com\/cn\/974667\/Demon","bnetURL":"http:\/\/www.battlenet.com.cn\/sc2\/zh\/profile\/974667\/1\/Demon\/"}],"division":{"points":462,"wins":28,"league":"platinum","region":"CN"},"rank":79},{"players":[{"race":"terran","name":"Joe","region":"AM","url":"http:\/\/www.sc2ranks.com\/us\/2249005\/Joe","bnetURL":"http:\/\/us.battle.net\/sc2\/en\/profile\/2249005\/1\/Joe\/"},{"race":"terran","name":"Lawbringer","region":"AM","url":"http:\/\/www.sc2ranks.com\/us\/1254062\/Lawbringer","bnetURL":"http:\/\/us.battle.net\/sc2\/en\/profile\/1254062\/1\/Lawbringer\/"}],"division":{"points":461,"wins":32,"league":"platinum","region":"AM"},"rank":80},{"players":[{"race":"protoss","name":"\u5931\u8272\u7684\u5f69\u753b","region":"CN","url":"http:\/\/www.sc2ranks.com\/cn\/367818\/%E5%A4%B1%E8%89%B2%E7%9A%84%E5%BD%A9%E7%94%BB","bnetURL":"http:\/\/www.battlenet.com.cn\/sc2\/zh\/profile\/367818\/1\/%E5%A4%B1%E8%89%B2%E7%9A%84%E5%BD%A9%E7%94%BB\/"},{"race":"zerg","name":"\u53cd\u8f6c\u5341\u5b57","region":"CN","url":"http:\/\/www.sc2ranks.com\/cn\/20416\/%E5%8F%8D%E8%BD%AC%E5%8D%81%E5%AD%97","bnetURL":"http:\/\/www.battlenet.com.cn\/sc2\/zh\/profile\/20416\/1\/%E5%8F%8D%E8%BD%AC%E5%8D%81%E5%AD%97\/"}],"division":{"points":460,"wins":45,"league":"platinum","region":"CN"},"rank":81},{"players":[{"race":"random","name":"ElGrande","region":"EU","url":"http:\/\/www.sc2ranks.com\/eu\/1935582\/ElGrande","bnetURL":"http:\/\/eu.battle.net\/sc2\/en\/profile\/1935582\/1\/ElGrande\/"},{"race":"protoss","name":"DrDestro","region":"EU","url":"http:\/\/www.sc2ranks.com\/eu\/714228\/DrDestro","bnetURL":"http:\/\/eu.battle.net\/sc2\/en\/profile\/714228\/1\/DrDestro\/"}],"division":{"points":460,"wins":29,"league":"platinum","region":"EU"},"rank":82},{"players":[{"race":"zerg","name":"\uace8\ub4c0\uacf5","region":"KR&TW","url":"http:\/\/www.sc2ranks.com\/kr\/1890364\/%EA%B3%A8%EB%93%80%EA%B3%B5","bnetURL":"http:\/\/kr.battle.net\/sc2\/ko\/profile\/1890364\/1\/%EA%B3%A8%EB%93%80%EA%B3%B5\/"},{"race":"protoss","name":"\uc774\uc774\uc774","region":"KR&TW","url":"http:\/\/www.sc2ranks.com\/kr\/2133107\/%EC%9D%B4%EC%9D%B4%EC%9D%B4","bnetURL":"http:\/\/kr.battle.net\/sc2\/ko\/profile\/2133107\/1\/%EC%9D%B4%EC%9D%B4%EC%9D%B4\/"}],"division":{"points":460,"wins":22,"league":"platinum","region":"KR&TW"},"rank":83},{"players":[{"race":"random","name":"sayID","region":"AM","url":"http:\/\/www.sc2ranks.com\/us\/284377\/sayID","bnetURL":"http:\/\/us.battle.net\/sc2\/en\/profile\/284377\/1\/sayID\/"},{"race":"terran","name":"iWishYouWell","region":"AM","url":"http:\/\/www.sc2ranks.com\/us\/1300552\/iWishYouWell","bnetURL":"http:\/\/us.battle.net\/sc2\/en\/profile\/1300552\/1\/iWishYouWell\/"}],"division":{"points":459,"wins":35,"league":"platinum","region":"AM"},"rank":84},{"players":[{"race":"zerg","name":"Robert","region":"AM","url":"http:\/\/www.sc2ranks.com\/us\/1239156\/Robert","bnetURL":"http:\/\/us.battle.net\/sc2\/en\/profile\/1239156\/1\/Robert\/"},{"race":"protoss","name":"SideWindeR","region":"AM","url":"http:\/\/www.sc2ranks.com\/us\/3257242\/SideWindeR","bnetURL":"http:\/\/us.battle.net\/sc2\/en\/profile\/3257242\/1\/SideWindeR\/"}],"division":{"points":459,"wins":17,"league":"platinum","region":"AM"},"rank":85},{"players":[{"race":"terran","name":"Xan","region":"SEA","url":"http:\/\/www.sc2ranks.com\/sea\/73041\/Xan","bnetURL":"http:\/\/sea.battle.net\/sc2\/en\/profile\/73041\/1\/Xan\/"},{"race":"protoss","name":"DaMyxxe","region":"SEA","url":"http:\/\/www.sc2ranks.com\/sea\/73467\/DaMyxxe","bnetURL":"http:\/\/sea.battle.net\/sc2\/en\/profile\/73467\/1\/DaMyxxe\/"}],"division":{"points":458,"wins":56,"league":"platinum","region":"SEA"},"rank":86},{"players":[{"race":"protoss","name":"Dwarfius","region":"EU","url":"http:\/\/www.sc2ranks.com\/eu\/1514743\/Dwarfius","bnetURL":"http:\/\/eu.battle.net\/sc2\/en\/profile\/1514743\/1\/Dwarfius\/"},{"race":"protoss","name":"Demion","region":"EU","url":"http:\/\/www.sc2ranks.com\/eu\/1327192\/Demion","bnetURL":"http:\/\/eu.battle.net\/sc2\/en\/profile\/1327192\/1\/Demion\/"}],"division":{"points":458,"wins":36,"league":"platinum","region":"EU"},"rank":87},{"players":[{"race":"zerg","name":"BioHazard","region":"EU","url":"http:\/\/www.sc2ranks.com\/eu\/266686\/BioHazard","bnetURL":"http:\/\/eu.battle.net\/sc2\/en\/profile\/266686\/1\/BioHazard\/"},{"race":"terran","name":"EXE","region":"EU","url":"http:\/\/www.sc2ranks.com\/eu\/462807\/EXE","bnetURL":"http:\/\/eu.battle.net\/sc2\/en\/profile\/462807\/1\/EXE\/"}],"division":{"points":457,"wins":47,"league":"platinum","region":"EU"},"rank":88},{"players":[{"race":"random","name":"SanFX","region":"EU","url":"http:\/\/www.sc2ranks.com\/eu\/335222\/SanFX","bnetURL":"http:\/\/eu.battle.net\/sc2\/en\/profile\/335222\/1\/SanFX\/"},{"race":"zerg","name":"Knave","region":"EU","url":"http:\/\/www.sc2ranks.com\/eu\/399114\/Knave","bnetURL":"http:\/\/eu.battle.net\/sc2\/en\/profile\/399114\/1\/Knave\/"}],"division":{"points":457,"wins":44,"league":"platinum","region":"EU"},"rank":89},{"players":[{"race":"zerg","name":"TomEEE","region":"AM","url":"http:\/\/www.sc2ranks.com\/us\/930975\/TomEEE","bnetURL":"http:\/\/us.battle.net\/sc2\/en\/profile\/930975\/1\/TomEEE\/"},{"race":"protoss","name":"TeddyG","region":"AM","url":"http:\/\/www.sc2ranks.com\/us\/859230\/TeddyG","bnetURL":"http:\/\/us.battle.net\/sc2\/en\/profile\/859230\/1\/TeddyG\/"}],"division":{"points":457,"wins":24,"league":"platinum","region":"AM"},"rank":90},{"players":[{"race":"random","name":"Stress","region":"AM","url":"http:\/\/www.sc2ranks.com\/us\/1007421\/Stress","bnetURL":"http:\/\/us.battle.net\/sc2\/en\/profile\/1007421\/1\/Stress\/"},{"race":"terran","name":"Kamwah","region":"AM","url":"http:\/\/www.sc2ranks.com\/us\/3173384\/Kamwah","bnetURL":"http:\/\/us.battle.net\/sc2\/en\/profile\/3173384\/1\/Kamwah\/"}],"division":{"points":457,"wins":23,"league":"platinum","region":"AM"},"rank":91},{"players":[{"race":"terran","name":"Cougarbait","region":"AM","url":"http:\/\/www.sc2ranks.com\/us\/1596800\/Cougarbait","bnetURL":"http:\/\/us.battle.net\/sc2\/en\/profile\/1596800\/1\/Cougarbait\/"},{"race":"zerg","name":"DirtyMike","region":"AM","url":"http:\/\/www.sc2ranks.com\/us\/377865\/DirtyMike","bnetURL":"http:\/\/us.battle.net\/sc2\/en\/profile\/377865\/1\/DirtyMike\/"}],"division":{"points":456,"wins":46,"league":"platinum","region":"AM"},"rank":92},{"players":[{"race":"terran","name":"Ace","region":"AM","url":"http:\/\/www.sc2ranks.com\/us\/3575760\/Ace","bnetURL":"http:\/\/us.battle.net\/sc2\/en\/profile\/3575760\/1\/Ace\/"},{"race":"random","name":"FeaRLesS","region":"AM","url":"http:\/\/www.sc2ranks.com\/us\/3613933\/FeaRLesS","bnetURL":"http:\/\/us.battle.net\/sc2\/en\/profile\/3613933\/1\/FeaRLesS\/"}],"division":{"points":456,"wins":22,"league":"platinum","region":"AM"},"rank":93},{"players":[{"race":"protoss","name":"crzyazn","region":"AM","url":"http:\/\/www.sc2ranks.com\/us\/842909\/crzyazn","bnetURL":"http:\/\/us.battle.net\/sc2\/en\/profile\/842909\/1\/crzyazn\/"},{"race":"terran","name":"OpFor","region":"AM","url":"http:\/\/www.sc2ranks.com\/us\/372018\/OpFor","bnetURL":"http:\/\/us.battle.net\/sc2\/en\/profile\/372018\/1\/OpFor\/"}],"division":{"points":455,"wins":76,"league":"platinum","region":"AM"},"rank":94},{"players":[{"race":"zerg","name":"N\u00f8X","region":"EU","url":"http:\/\/www.sc2ranks.com\/eu\/2411983\/N%C3%B8X","bnetURL":"http:\/\/eu.battle.net\/sc2\/en\/profile\/2411983\/1\/N%C3%B8X\/"},{"race":"protoss","name":"Ulz","region":"EU","url":"http:\/\/www.sc2ranks.com\/eu\/1614225\/Ulz","bnetURL":"http:\/\/eu.battle.net\/sc2\/en\/profile\/1614225\/1\/Ulz\/"}],"division":{"points":455,"wins":51,"league":"platinum","region":"EU"},"rank":95},{"players":[{"race":"random","name":"Optimus","region":"EU","url":"http:\/\/www.sc2ranks.com\/eu\/490592\/Optimus","bnetURL":"http:\/\/eu.battle.net\/sc2\/en\/profile\/490592\/1\/Optimus\/"},{"race":"protoss","name":"TobSucht","region":"EU","url":"http:\/\/www.sc2ranks.com\/eu\/2601827\/TobSucht","bnetURL":"http:\/\/eu.battle.net\/sc2\/en\/profile\/2601827\/1\/TobSucht\/"}],"division":{"points":455,"wins":47,"league":"platinum","region":"EU"},"rank":96},{"players":[{"race":"terran","name":"AMBROSIUS","region":"EU","url":"http:\/\/www.sc2ranks.com\/eu\/1808191\/AMBROSIUS","bnetURL":"http:\/\/eu.battle.net\/sc2\/en\/profile\/1808191\/1\/AMBROSIUS\/"},{"race":"protoss","name":"deepspace","region":"EU","url":"http:\/\/www.sc2ranks.com\/eu\/1031957\/deepspace","bnetURL":"http:\/\/eu.battle.net\/sc2\/en\/profile\/1031957\/1\/deepspace\/"}],"division":{"points":455,"wins":30,"league":"platinum","region":"EU"},"rank":97},{"players":[{"race":"terran","name":"Terranysaur","region":"AM","url":"http:\/\/www.sc2ranks.com\/us\/2929397\/Terranysaur","bnetURL":"http:\/\/us.battle.net\/sc2\/en\/profile\/2929397\/1\/Terranysaur\/"},{"race":"protoss","name":"PROTOStitute","region":"AM","url":"http:\/\/www.sc2ranks.com\/us\/921956\/PROTOStitute","bnetURL":"http:\/\/us.battle.net\/sc2\/en\/profile\/921956\/1\/PROTOStitute\/"}],"division":{"points":455,"wins":30,"league":"platinum","region":"AM"},"rank":97},{"players":[{"race":"protoss","name":"Agalilex","region":"EU","url":"http:\/\/www.sc2ranks.com\/eu\/1589422\/Agalilex","bnetURL":"http:\/\/eu.battle.net\/sc2\/en\/profile\/1589422\/1\/Agalilex\/"},{"race":"terran","name":"BzhImperato","region":"EU","url":"http:\/\/www.sc2ranks.com\/eu\/1664177\/BzhImperato","bnetURL":"http:\/\/eu.battle.net\/sc2\/en\/profile\/1664177\/1\/BzhImperato\/"}],"division":{"points":454,"wins":57,"league":"platinum","region":"EU"},"rank":98}]